LICENSE
README.md
favicon.ico
setup.cfg
setup.py
metREx/__init__.py
metREx/manage.py
metREx.egg-info/PKG-INFO
metREx.egg-info/SOURCES.txt
metREx.egg-info/dependency_links.txt
metREx.egg-info/entry_points.txt
metREx.egg-info/not-zip-safe
metREx.egg-info/requires.txt
metREx.egg-info/top_level.txt
metREx/app/__init__.py
metREx/app/main/__init__.py
metREx/app/main/config.py
metREx/app/main/api/__init__.py
metREx/app/main/api/appd/__init__.py
metREx/app/main/api/extrahop/__init__.py
metREx/app/main/api/github/__init__.py
metREx/app/main/api/graphite/__init__.py
metREx/app/main/api/newrelic/__init__.py
metREx/app/main/api/pushgateway/__init__.py
metREx/app/main/api/wavefront/__init__.py
metREx/app/main/controller/__init__.py
metREx/app/main/controller/metrics_controller.py
metREx/app/main/controller/scheduler_controller.py
metREx/app/main/database/__init__.py
metREx/app/main/database/bigquery/__init__.py
metREx/app/main/database/bigquery/dialect/__init__.py
metREx/app/main/database/db2/__init__.py
metREx/app/main/database/db2/dialect/__init__.py
metREx/app/main/database/postgresql/__init__.py
metREx/app/main/database/postgresql/dialect/__init__.py
metREx/app/main/service/__init__.py
metREx/app/main/service/metrics_service.py
metREx/app/main/util/__init__.py
metREx/app/main/util/api_helper.py
metREx/app/main/util/apscheduler_helper.py
metREx/app/main/util/dto.py
metREx/app/main/util/flask_helper.py
metREx/app/main/util/misc_helper.py
metREx/app/main/util/multiprocessing_helper.py
metREx/app/main/util/prometheus_helper.py
metREx/app/main/util/sqlalchemy_helper.py