Metadata-Version: 2.1
Name: metREx
Version: 0.7.2
Summary: SQL query and monitoring system metrics exporter for Prometheus
Home-page: https://github.com/homedepot/metREx
Author: Mike Phillipson
Author-email: MICHAEL_PHILLIPSON1@homedepot.com
License: Apache 2.0
Keywords: prometheus exporter prometheus-exporter metrics metrics-exporter query-exporter sql sql-exporter appd appd-exporter appdynamics appdynamics-exporter extrahop extrahop-exporter
Platform: UNKNOWN
Requires-Python: >=3.6
Provides-Extra: bigquery
Provides-Extra: mssql
Provides-Extra: mysql
Provides-Extra: oracle
Provides-Extra: postgresql
Provides-Extra: sqlite
Provides-Extra: db2
Provides-Extra: informix
License-File: LICENSE
